[{"name": "Pineapple", "max": 100.0, "min": 5.07, "avr": 50.9229426433915}, {"name": "Banana", "max": 99.91, "min": 5.03, "avr": 52.568630806845924}, {"name": "Guava", "max": 99.79, "min": 5.02, "avr": 51.626132315521645}, {"name": "Cherry", "max": 99.92, "min": 5.23, "avr": 53.77449152542373}, {"name": "Blueberry", "max": 99.23, "min": 5.1, "avr": 52.98620052770449}, {"name": "Plum", "max": 99.88, "min": 5.15, "avr": 52.481679999999976}, {"name": "Cranberry", "max": 99.47, "min": 5.17, "avr": 50.8735092348285}, {"name": "Grapes", "max": 99.93, "min": 5.06, "avr": 51.400527638190944}, {"name": "Raspberry", "max": 99.93, "min": 5.12, "avr": 53.13444444444448}, {"name": "Boysenberry", "max": 99.74, "min": 5.07, "avr": 52.73598820059}, {"name": "Orange", "max": 99.88, "min": 5.09, "avr": 51.256956521739156}, {"name": "Mango", "max": 99.64, "min": 5.13, "avr": 53.31888888888896}, {"name": "Apricot", "max": 99.74, "min": 5.0, "avr": 52.49144278606965}, {"name": "Melon", "max": 99.64, "min": 5.45, "avr": 51.6136386768448}, {"name": "Kiwifruit", "max": 99.94, "min": 5.11, "avr": 53.261974025974055}, {"name": "Papaya", "max": 99.64, "min": 5.07, "avr": 52.00638743455493}, {"name": "Apple", "max": 99.74, "min": 5.1, "avr": 50.443826530612235}, {"name": "Peach", "max": 99.77, "min": 5.19, "avr": 52.34562162162166}, {"name": "Strawberry", "max": 99.7, "min": 5.95, "avr": 51.8095128205128}, {"name": "Blackberry", "max": 99.99, "min": 5.29, "avr": 52.81224489795914}]